{"name":"Sound Bomber","tagline":"Send sounds to friends!","body":"### Sound Bomber\r\n\r\nEver wanted to send sounds to friends? Get tired of boring \"making noises\" the old fashioned way with your mouth? WELL WORRY NO MORE!\r\n\r\nINTRODUCING... SOUND BOMBER!\r\n\r\nSound Bomber allows users to connect to Facebook and send push notifications to their friends that make noise when received by the other user. \r\n\r\nBUT WAIT, THERES MORE:\r\n\r\nSound Bomber can also be used locally to make noises, featuring fun animations and the ability to put any picture on the speaker. THAT'S RIGHT, ANY PICTURE can be blended into the speaker for INFINITE amounts of fun.\r\n\r\nBUT THAT'S NOT ALL:\r\n\r\nSound Bomber also features iWatch support, allowing users to instantly respond to their friends' sounds with sweet, sweet revenge from their wrists. Users can also use their watches to send farts to their phone locally.\r\n\r\n###Support\r\nHave an issue or suggestion? Email me at jakesaf@earthlink.net","google":"","note":"Don't delete this file! It's used internally to help with page regeneration."}